ktwcoding/__init__.py
ktwcoding/ktwcoding.py
ktwcoding-0.1.dist-info/METADATA
ktwcoding-0.1.dist-info/WHEEL
ktwcoding-0.1.dist-info/top_level.txt
ktwcoding-0.1.dist-info/RECORD
