Metadata-Version: 2.1
Name: ktwcoding
Version: 0.1
Summary: Python functions for controlling Arduino devices
Home-page: UNKNOWN
Author: taeu
Author-email: rlaxodn0428@naver.com
License: UNKNOWN
Platform: UNKNOWN
Requires-Dist: pyserial
